{
  "schema_version": "execution_result_v1",
  "task_id": "f7a3a4da-f6ca-4f57-8b4a-d2c42abf3fd6",
  "status": "SUCCESS",
  "summary": "Created countdowns table migration with share_token BEFORE INSERT trigger (retry loop, up to 5 attempts), set_updated_at BEFORE UPDATE trigger, three indexes (user_id, share_token UNIQUE, target_date), RLS enabled, and rollback comment block.",
  "changed_files": [
    "supabase/migrations/20260403000001_create_countdowns.sql"
  ],
  "artifacts": [
    "supabase/migrations/20260403000001_create_countdowns.sql",
    "summary.md"
  ],
  "tests": {
    "ran": false,
    "passed": false
  },
  "approval_flags": [],
  "issues": [],
  "next_actions": [
    "Apply migration via Supabase dashboard SQL editor or supabase db push",
    "Add RLS policies for SELECT/INSERT/UPDATE/DELETE (stubs included in migration file comments)",
    "Run generate_typescript_types to update src/types/database.ts"
  ]
}
